di/__init__.py
di/di.py
dinjector-2.1.0.dist-info/LICENCE.txt
dinjector-2.1.0.dist-info/METADATA
dinjector-2.1.0.dist-info/WHEEL
dinjector-2.1.0.dist-info/RECORD
