Metadata-Version: 2.1
Name: dinjector
Version: 2.1.0
Summary: Very simple dependency injector using a yaml file
License: LGPL
Author: Salvador Ruiz
Author-email: sruiz@indoorclima.com
Requires-Python: >=3.11,<4.0
Classifier: License :: Other/Proprietary License
Classifier: Programming Language :: Python :: 3
Classifier: Programming Language :: Python :: 3.11
Classifier: Programming Language :: Python :: 3.12
Requires-Dist: cfg-service (>=0.1.0,<0.2.0)
Requires-Dist: pyyaml (>=6.0,<7.0)
